<xilinx:hls_fe_msgs>
    <msg msg_groups="PRAGMA_VERBOSE_DUMP" msg_id="207-5471" msg_severity="WARNING" msg_loc="/home/gabriel/Documents/UFRGS/RAISE/ahls_resource_estimation/run_hls.tcl:16:9" msg_body="HLS pragma dump">
        <args ARG_PragmaContext="directive" ARG_PragmaFunction="correlation" ARG_PragmaIsValid="1" ARG_PragmaOptions="name=correlation" ARG_PragmaType="top" ClangWarningOption="dump-hls-pragmas"/>
    </msg>
    <msg msg_groups="PRAGMA_UNROLL" msg_id="214-291" msg_severity="INFO" msg_loc="HLS-benchmarks/C-Slow/correlation/correlation.cpp:60:7" msg_body="Loop 'loop_4' is marked as complete unroll implied by the pipeline pragma">
        <args LoopName="loop_4"/>
    </msg>
    <msg msg_groups="PRAGMA_UNROLL" msg_id="214-291" msg_severity="INFO" msg_loc="HLS-benchmarks/C-Slow/correlation/correlation.cpp:20:5" msg_body="Loop 'loop_1' is marked as complete unroll implied by the pipeline pragma">
        <args LoopName="loop_1"/>
    </msg>
    <msg msg_groups="PRAGMA_UNROLL" msg_id="214-291" msg_severity="INFO" msg_loc="HLS-benchmarks/C-Slow/correlation/correlation.cpp:27:5" msg_body="Loop 'loop_2' is marked as complete unroll implied by the pipeline pragma">
        <args LoopName="loop_2"/>
    </msg>
    <msg msg_groups="PRAGMA_UNROLL" msg_id="214-186" msg_severity="INFO" msg_loc="HLS-benchmarks/C-Slow/correlation/correlation.cpp:13:0" msg_body="Unrolling loop 'loop_4' (HLS-benchmarks/C-Slow/correlation/correlation.cpp:60:7) in function 'correlation' completely with a factor of 32">
        <args Factor="32" LoopLoc="HLS-benchmarks/C-Slow/correlation/correlation.cpp:60:7" LoopName="loop_4"/>
    </msg>
    <msg msg_groups="PRAGMA_UNROLL" msg_id="214-186" msg_severity="INFO" msg_loc="HLS-benchmarks/C-Slow/correlation/correlation.cpp:13:0" msg_body="Unrolling loop 'loop_1' (HLS-benchmarks/C-Slow/correlation/correlation.cpp:20:5) in function 'correlation' completely with a factor of 32">
        <args Factor="32" LoopLoc="HLS-benchmarks/C-Slow/correlation/correlation.cpp:20:5" LoopName="loop_1"/>
    </msg>
    <msg msg_groups="PRAGMA_UNROLL" msg_id="214-186" msg_severity="INFO" msg_loc="HLS-benchmarks/C-Slow/correlation/correlation.cpp:13:0" msg_body="Unrolling loop 'loop_2' (HLS-benchmarks/C-Slow/correlation/correlation.cpp:27:5) in function 'correlation' completely with a factor of 32">
        <args Factor="32" LoopLoc="HLS-benchmarks/C-Slow/correlation/correlation.cpp:27:5" LoopName="loop_2"/>
    </msg>
</xilinx:hls_fe_msgs>

